LICENSE.txt
MANIFEST.in
README.rst
requirements.txt
setup.py
pto/__init__.py
pto.egg-info/PKG-INFO
pto.egg-info/SOURCES.txt
pto.egg-info/dependency_links.txt
pto.egg-info/not-zip-safe
pto.egg-info/requires.txt
pto.egg-info/top_level.txt