Metadata-Version: 1.0
Name: pto
Version: 0.0.6
Summary: Timeouts for arbitrary Python functions.
Home-page: UNKNOWN
Author: Hank Gay
Author-email: hank.gay@gmail.com/
License: Copyright (c) 2013 Hank Gay
